CHANGELOG.rst
MANIFEST.in
README.rst
setup.py
redmine_releasedate.egg-info/PKG-INFO
redmine_releasedate.egg-info/SOURCES.txt
redmine_releasedate.egg-info/dependency_links.txt
redmine_releasedate.egg-info/entry_points.txt
redmine_releasedate.egg-info/requires.txt
redmine_releasedate.egg-info/top_level.txt
releasedate/__init__.py
releasedate/jenkins.py
releasedate/redmine.py
releasedate/repo.py
releasedate/server.py