Metadata-Version: 1.0
Name: redmine-releasedate
Version: 0.1.2
Summary: Track when your features are shipped to production in Redmine.
Home-page: https://github.com/futurecolors/redmine-releasedate
Author: Ilya Baryshev
Author-email: baryhsev@gmail.com
License: MIT
Platform: UNKNOWN
